LICENSE
MANIFEST.in
README.md
setup.cfg
setup.py
PolymerCpp/__init__.py
PolymerCpp/algorithms.py
PolymerCpp/helpers.py
PolymerCpp.egg-info/PKG-INFO
PolymerCpp.egg-info/SOURCES.txt
PolymerCpp.egg-info/dependency_links.txt
PolymerCpp.egg-info/requires.txt
PolymerCpp.egg-info/top_level.txt
PolymerCpp/core/Misc.cpp
PolymerCpp/core/Path.cpp
PolymerCpp/core/Path2D.cpp
PolymerCpp/core/PolymerCpp.cpp
PolymerCpp/core/PyUtils.cpp
PolymerCpp/core/RgDict.cpp
PolymerCpp/core/SAWLC.cpp
PolymerCpp/core/SAWLC_Rosenbluth.cpp
PolymerCpp/core/Stdafx.cpp
PolymerCpp/core/Stopwatch.cpp
PolymerCpp/core/WLC.cpp
PolymerCpp/core/WLC2D.cpp
include/Misc.h
include/Path.h
include/Path2D.h
include/PyUtils.h
include/RgDict.h
include/SAWLC.h
include/SAWLC_Rosenbluth.h
include/Stdafx.h
include/Stopwatch.h
include/WLC.h
include/WLC2D.h
include/Eigen/CMakeLists.txt
include/Eigen/COPYING.BSD
include/Eigen/COPYING.GPL
include/Eigen/COPYING.LGPL
include/Eigen/COPYING.MINPACK
include/Eigen/COPYING.MPL2
include/Eigen/COPYING.README
include/Eigen/Cholesky
include/Eigen/CholmodSupport
include/Eigen/Core
include/Eigen/Dense
include/Eigen/Eigen
include/Eigen/Eigenvalues
include/Eigen/Geometry
include/Eigen/Householder
include/Eigen/IterativeLinearSolvers
include/Eigen/Jacobi
include/Eigen/LU
include/Eigen/MetisSupport
include/Eigen/OrderingMethods
include/Eigen/PaStiXSupport
include/Eigen/PardisoSupport
include/Eigen/QR
include/Eigen/QtAlignedMalloc
include/Eigen/SPQRSupport
include/Eigen/SVD
include/Eigen/Sparse
include/Eigen/SparseCholesky
include/Eigen/SparseCore
include/Eigen/SparseLU
include/Eigen/SparseQR
include/Eigen/StdDeque
include/Eigen/StdList
include/Eigen/StdVector
include/Eigen/SuperLUSupport
include/Eigen/UmfPackSupport
include/Eigen/version.txt
include/Eigen/src/Cholesky/LDLT.h
include/Eigen/src/Cholesky/LLT.h
include/Eigen/src/Cholesky/LLT_LAPACKE.h
include/Eigen/src/CholmodSupport/CholmodSupport.h
include/Eigen/src/Core/Array.h
include/Eigen/src/Core/ArrayBase.h
include/Eigen/src/Core/ArrayWrapper.h
include/Eigen/src/Core/Assign.h
include/Eigen/src/Core/AssignEvaluator.h
include/Eigen/src/Core/Assign_MKL.h
include/Eigen/src/Core/BandMatrix.h
