Metadata-Version: 2.4
Name: PolymerCpp
Version: 0.1.4
Summary: 2D and 3D wormlike chain generator for Python and written in C++
Home-page: https://github.com/kmdouglass/PolymerCpp
Download-URL: https://github.com/kmdouglass/PolymerCpp/archive/v0.1.4.tar.gz
Author: Kyle M. Douglass, Marcel Stefko
Author-email: kyle.m.douglass@gmail.com
License: License :: OSI Approved :: GNU General Public License v3 (GPLv3)
Keywords: polymer,wormlike chain,random walk
Classifier: Topic :: Scientific/Engineering :: Physics
Classifier: Programming Language :: Python :: 3
License-File: LICENSE
Requires-Dist: numpy>=1.11.0
Requires-Dist: matplotlib>=2.0.0
Dynamic: author
Dynamic: author-email
Dynamic: classifier
Dynamic: download-url
Dynamic: home-page
Dynamic: keywords
Dynamic: license
Dynamic: license-file
Dynamic: requires-dist
Dynamic: summary
